odoo8_addon_base_location_nuts-8.0.2.0.0.99.dev14-py2.7-nspkg.pth
odoo8_addon_base_location_nuts-8.0.2.0.0.99.dev14.dist-info/DESCRIPTION.rst
odoo8_addon_base_location_nuts-8.0.2.0.0.99.dev14.dist-info/METADATA
odoo8_addon_base_location_nuts-8.0.2.0.0.99.dev14.dist-info/RECORD
odoo8_addon_base_location_nuts-8.0.2.0.0.99.dev14.dist-info/WHEEL
odoo8_addon_base_location_nuts-8.0.2.0.0.99.dev14.dist-info/metadata.json
odoo8_addon_base_location_nuts-8.0.2.0.0.99.dev14.dist-info/namespace_packages.txt
odoo8_addon_base_location_nuts-8.0.2.0.0.99.dev14.dist-info/top_level.txt
odoo_addons/base_location_nuts/README.rst
odoo_addons/base_location_nuts/__init__.py
odoo_addons/base_location_nuts/__openerp__.py
odoo_addons/base_location_nuts/i18n/base_location_nuts.pot
odoo_addons/base_location_nuts/i18n/de.po
odoo_addons/base_location_nuts/i18n/es.po
odoo_addons/base_location_nuts/i18n/eu.po
odoo_addons/base_location_nuts/i18n/fi.po
odoo_addons/base_location_nuts/i18n/it.po
odoo_addons/base_location_nuts/i18n/sl.po
odoo_addons/base_location_nuts/images/new_fields.png
odoo_addons/base_location_nuts/models/__init__.py
odoo_addons/base_location_nuts/models/res_country.py
odoo_addons/base_location_nuts/models/res_partner.py
odoo_addons/base_location_nuts/models/res_partner_nuts.py
odoo_addons/base_location_nuts/security/ir.model.access.csv
odoo_addons/base_location_nuts/static/description/icon.png
odoo_addons/base_location_nuts/views/res_country_view.xml
odoo_addons/base_location_nuts/views/res_partner_nuts_view.xml
odoo_addons/base_location_nuts/views/res_partner_view.xml
odoo_addons/base_location_nuts/wizard/__init__.py
odoo_addons/base_location_nuts/wizard/nuts_import.py
odoo_addons/base_location_nuts/wizard/nuts_import_view.xml
